{"issuedOn": "*|DATE|*", "@context": ["https://w3id.org/openbadges/v2", "https://w3id.org/blockcerts/v2", {"displayHtml": {"@id": "schema:description"},"firstname": {"@id": "schema:description"},"lastname": {"@id": "schema:description"},"competencyname": {"@id": "schema:description"},"templateid": {"@id": "schema:description"},"certificatepng": {"@id": "schema:description"},"version": {"@id": "schema:description"}}], "type": "Assertion","displayHtml": "" , "verification": {"type": ["MerkleProofVerification2017", "Extension"], "publicKey": "ecdsa-koblitz-pubkey:mwCGi6jve6s2cSmMoRQ5QmC5PnG7u6DnYw"}, "id": "urn:uuid:*|CERTUID|*","recipient": {"hashed": false, "type": "email", "identity": "*|EMAIL|*"}, "recipientProfile": {"type": ["RecipientProfile", "Extension"], "name": "*|NAME|*", "publicKey": "ecdsa-koblitz-pubkey:*|PUBKEY|*"}, "type": "Assertion", "badge": {"image": "", "issuer": {"image": "", "revocationList": "https://www.blockcerts.org/samples/2.0/revocation-list-testnet.json", "id": "http://18.221.73.39/blockchain/issuer.json", "type": "Profile", "name": "University of Blockchain", "email": "contact@issuer.org", "url": "https://www.issuer.org"}, "criteria": {"narrative": ""}, "signatureLines": [{"image": "", "type": ["SignatureLine", "Extension"], "name": "Your signature", "jobTitle": "University Issuer"}], "description": "", "id": "urn:uuid:82a4c9f2-3588-457b-80ea-da695571b8fc", "type": "BadgeClass", "name": "POST GRADUATE DIPLOMA IN MANAGEMENT"}}